CulturelandPython/__init__.py
CulturelandPython/client.py
CulturelandPython/login.py
CulturelandPython/redeemCode.py
CulturelandPython-0.1.2.dist-info/LICENSE
CulturelandPython-0.1.2.dist-info/METADATA
CulturelandPython-0.1.2.dist-info/WHEEL
CulturelandPython-0.1.2.dist-info/top_level.txt
CulturelandPython-0.1.2.dist-info/RECORD
